bipf/__init__.py
bipf-0.0.8.dist-info/LICENSE
bipf-0.0.8.dist-info/METADATA
bipf-0.0.8.dist-info/WHEEL
bipf-0.0.8.dist-info/top_level.txt
bipf-0.0.8.dist-info/RECORD
