Metadata-Version: 2.1
Name: bipf
Version: 0.0.8
Summary: A Python Library for the Binary In-Place Format (BIPF)
Home-page: https://github.com/cn-uofbasel/bipf-python
Author: Christian Tschudin
Author-email: christian.tschudin@unibas.ch
License: UNKNOWN
Platform: UNKNOWN
Classifier: Programming Language :: Python :: 3
Classifier: License :: OSI Approved :: MIT License
Classifier: Operating System :: OS Independent
Requires-Python: >=3.7
License-File: LICENSE
